pysgn/__init__.py
pysgn/geo_barabasi_albert_network.py
pysgn/geo_erdos_renyi_network.py
pysgn/geo_watts_strogatz_network.py
pysgn/ordering.py
pysgn/utils.py
pysgn-0.3.1.dist-info/METADATA
pysgn-0.3.1.dist-info/WHEEL
pysgn-0.3.1.dist-info/licenses/LICENSE
pysgn-0.3.1.dist-info/RECORD
