Metadata-Version: 2.4
Name: pysgn
Version: 0.3.1
Summary: A Python package for constructing synthetic geospatial networks
Project-URL: homepage, https://github.com/wang-boyu/pysgn
Project-URL: repository, https://github.com/wang-boyu/pysgn
Author-email: Boyu Wang <bwang44@buffalo.edu>
License: MIT
License-File: LICENSE
Requires-Python: >=3.10
Requires-Dist: geopandas
Requires-Dist: loguru
Requires-Dist: networkx
Requires-Dist: numpy
Requires-Dist: pandas
Requires-Dist: scikit-learn
Requires-Dist: scipy
Requires-Dist: tqdm
Provides-Extra: all
Requires-Dist: black[jupyter]; extra == 'all'
Requires-Dist: contextily; extra == 'all'
Requires-Dist: coverage; extra == 'all'
Requires-Dist: ipython; extra == 'all'
Requires-Dist: ipywidgets; extra == 'all'
Requires-Dist: isort; extra == 'all'
Requires-Dist: jupyterlab; extra == 'all'
Requires-Dist: jupyterlab-code-formatter; extra == 'all'
Requires-Dist: jupyterlab-execute-time; extra == 'all'
Requires-Dist: jupyterlab-lsp; extra == 'all'
Requires-Dist: matplotlib; extra == 'all'
Requires-Dist: myst-nb; extra == 'all'
Requires-Dist: myst-parser; extra == 'all'
Requires-Dist: pre-commit; extra == 'all'
Requires-Dist: pydata-sphinx-theme; extra == 'all'
Requires-Dist: pytest-cov; extra == 'all'
Requires-Dist: pytest-mock; extra == 'all'
Requires-Dist: pytest>=4.6; extra == 'all'
Requires-Dist: python-lsp-server; extra == 'all'
Requires-Dist: ruff; extra == 'all'
Requires-Dist: seaborn; extra == 'all'
Requires-Dist: sphinx; extra == 'all'
Provides-Extra: dev
Requires-Dist: black[jupyter]; extra == 'dev'
Requires-Dist: coverage; extra == 'dev'
Requires-Dist: pre-commit; extra == 'dev'
Requires-Dist: pytest-cov; extra == 'dev'
Requires-Dist: pytest-mock; extra == 'dev'
Requires-Dist: pytest>=4.6; extra == 'dev'
Requires-Dist: ruff; extra == 'dev'
Requires-Dist: sphinx; extra == 'dev'
Provides-Extra: docs
Requires-Dist: contextily; extra == 'docs'
Requires-Dist: ipython; extra == 'docs'
Requires-Dist: ipywidgets; extra == 'docs'
Requires-Dist: isort; extra == 'docs'
Requires-Dist: jupyterlab; extra == 'docs'
Requires-Dist: jupyterlab-code-formatter; extra == 'docs'
Requires-Dist: jupyterlab-execute-time; extra == 'docs'
Requires-Dist: jupyterlab-lsp; extra == 'docs'
Requires-Dist: matplotlib; extra == 'docs'
Requires-Dist: myst-nb; extra == 'docs'
Requires-Dist: myst-parser; extra == 'docs'
Requires-Dist: pydata-sphinx-theme; extra == 'docs'
Requires-Dist: python-lsp-server; extra == 'docs'
Requires-Dist: seaborn; extra == 'docs'
Requires-Dist: sphinx; extra == 'docs'
